octuner/__init__.py
octuner/config/__init__.py
octuner/config/loader.py
octuner/discovery/__init__.py
octuner/discovery/discovery.py
octuner/optimization/__init__.py
octuner/optimization/auto.py
octuner/optimization/executor.py
octuner/optimization/optimizer.py
octuner/providers/__init__.py
octuner/providers/base.py
octuner/providers/gemini.py
octuner/providers/openai.py
octuner/providers/registry.py
octuner/tunable/__init__.py
octuner/tunable/mixin.py
octuner/tunable/registry.py
octuner/tunable/tunable_llm.py
octuner/tunable/types.py
octuner/utils/__init__.py
octuner/utils/exporter.py
octuner/utils/patcher.py
octuner/utils/setter.py
octuner-0.1.2.post1.dist-info/METADATA
octuner-0.1.2.post1.dist-info/WHEEL
octuner-0.1.2.post1.dist-info/RECORD
