Metadata-Version: 2.4
Name: octuner
Version: 0.1.2.post1
Summary: A lightweight Python library that automatically discovers, evaluates, and tunes parameters of multi-provider LLM pipelines to balance quality, cost, and latency.
Project-URL: Homepage, https://github.com/joaoplay/octuner
Project-URL: Repository, https://github.com/joaoplay/octuner
Project-URL: Documentation, https://joaoplay.github.io/octuner
Project-URL: Bug Tracker, https://github.com/joaoplay/octuner/issues
Author-email: João Braz Simões <joaosbraz@gmail.com>
License: MIT
Keywords: auto-tuning,gemini,hyperparameter-optimization,large-language-models,llm,model-selection,multi-provider,openai,optuna,parameter-tuning,prompt-engineering
Classifier: Development Status :: 4 - Beta
Classifier: Intended Audience :: Developers
Classifier: License :: OSI Approved :: MIT License
Classifier: Operating System :: OS Independent
Classifier: Programming Language :: Python :: 3
Classifier: Programming Language :: Python :: 3 :: Only
Classifier: Programming Language :: Python :: 3.10
Classifier: Programming Language :: Python :: 3.11
Classifier: Programming Language :: Python :: 3.12
Classifier: Topic :: Scientific/Engineering :: Artificial Intelligence
Classifier: Topic :: Software Development :: Libraries :: Python Modules
Requires-Python: >=3.10
Requires-Dist: google-genai>=0.8.5
Requires-Dist: openai>=1.101.0
Requires-Dist: optuna>=3.0.0
Requires-Dist: pyyaml>=6.0
Requires-Dist: typing-extensions>=4.0.0; python_version < '3.12'
Provides-Extra: dev
Requires-Dist: black>=23.0.0; extra == 'dev'
Requires-Dist: isort>=5.12.0; extra == 'dev'
Requires-Dist: mypy>=1.0.0; extra == 'dev'
Requires-Dist: pytest-asyncio>=0.21.0; extra == 'dev'
Requires-Dist: pytest-cov>=4.0.0; extra == 'dev'
Requires-Dist: pytest>=7.0.0; extra == 'dev'
Requires-Dist: ruff>=0.1.0; extra == 'dev'
Provides-Extra: docs
Requires-Dist: mkdocs-material>=9.6.20; extra == 'docs'
Requires-Dist: mkdocs-minify-plugin>=0.8.0; extra == 'docs'
Requires-Dist: mkdocstrings-python>=1.7.0; extra == 'docs'
Requires-Dist: mkdocstrings[python]>=0.24.0; extra == 'docs'
Provides-Extra: examples
Requires-Dist: openai>=1.0.0; extra == 'examples'
